<annotation>
	<folder>data</folder>
	<filename>00000120.jpg</filename>
	<path>C:\Users\Batuhan\source\repos\data_generator\data_generator\data\00000120.jpg</path>
	<source>
		<database>Unknown</database>
	</source>
	<size>
		<width>350</width>
		<height>400</height>
		<depth>3</depth>
	</size>
	<segmented>0</segmented>
	<object>
		<name>ball</name>
		<pose>Unspecified</pose>
		<truncated>0</truncated>
		<difficult>0</difficult>
		<bndbox>
			<xmin>8</xmin>
			<ymin>328</ymin>
			<xmax>70</xmax>
			<ymax>389</ymax>
		</bndbox>
	</object>
</annotation>
